setup.py
svc_test/__init__.py
svc_test.egg-info/PKG-INFO
svc_test.egg-info/SOURCES.txt
svc_test.egg-info/dependency_links.txt
svc_test.egg-info/top_level.txt