Metadata-Version: 1.0
Name: svc-test
Version: 0.0.1
Summary: svc test
Home-page: http://svc.sogou
Author: ywt
Author-email: yinwentao@sogou-inc.com
License: MIT License
Keywords: svc,test,egg
Platform: any
